qmlpandas/__init__.py
qmlpandas/parsing.py
qmlpandas/util.py
qmlpandas-0.0.1.dist-info/LICENSE
qmlpandas-0.0.1.dist-info/METADATA
qmlpandas-0.0.1.dist-info/WHEEL
qmlpandas-0.0.1.dist-info/top_level.txt
qmlpandas-0.0.1.dist-info/RECORD
