Metadata-Version: 2.1
Name: qmlpandas
Version: 0.0.1
Summary: A simple parser for QGIS style files to pandas DataFrame
Author: Bas Altena
Author-email: b.altena@zuiderzeeland.nl
License: APACHE
Requires-Python: >=3.12
License-File: LICENSE
Requires-Dist: pandas
